nsemine/__init__.py
nsemine/fno.py
nsemine/generic.py
nsemine/historical.py
nsemine/live.py
nsemine/nse.py
nsemine/bin/__init__.py
nsemine/bin/auth.py
nsemine/bin/scraper.py
nsemine/utilities/__init__.py
nsemine/utilities/tokens.py
nsemine/utilities/urls.py
nsemine/utilities/utils.py
nsemine-1.3.dist-info/licenses/LICENSE
nsemine-1.3.dist-info/METADATA
nsemine-1.3.dist-info/WHEEL
nsemine-1.3.dist-info/top_level.txt
nsemine-1.3.dist-info/RECORD
