Metadata-Version: 2.4
Name: nsemine
Version: 1.3
Summary: Efficient and Reliable Python Library for Scraping Real-Time and Historical Data of Stocks, Futures, Options and Indices From The NSE Exchange.
Author-email: kbizme <kbhowmik.eduz@gmail.com>
Maintainer-email: kbizme <kbhowmik.eduz@gmail.com>
License-Expression: MIT
Project-URL: Homepage, https://github.com/kbizme/nsemine
Project-URL: Bug Tracker, https://github.com/kbizme/nsemine/issues
Keywords: nse,nsemine,indian stock data,stock market,financial data,scraping,indices,stocks,futures,options,trading,investment,nse exchange,nifty data,nse scrapers,stock data,nse python library
Classifier: Programming Language :: Python :: 3
Classifier: Operating System :: OS Independent
Classifier: Topic :: Office/Business :: Financial
Classifier: Topic :: Internet :: WWW/HTTP :: Indexing/Search
Classifier: Topic :: Software Development :: Libraries
Classifier: Intended Audience :: Developers
Classifier: Intended Audience :: Financial and Insurance Industry
Classifier: Intended Audience :: Science/Research
Classifier: Intended Audience :: Education
Requires-Python: >=3.6
License-File: LICENSE
Requires-Dist: aiohttp
Requires-Dist: asyncio
Requires-Dist: certifi
Requires-Dist: charset-normalizer
Requires-Dist: idna
Requires-Dist: numpy
Requires-Dist: pandas
Requires-Dist: python-dateutil
Requires-Dist: pytz
Requires-Dist: requests
Requires-Dist: six
Requires-Dist: tzdata
Requires-Dist: urllib3
Requires-Dist: brotli
Requires-Dist: zstandard
Requires-Dist: yarl
Dynamic: license-file
